nandtool/__init__.py
nandtool/__main__.py
nandtool/config.py
nandtool/configs/Jaguar_InControl_Touch.toml
nandtool/configs/Mercedes_Hermes_2.toml
nandtool/configs/Mercedes_Hermes_2_noecc.toml
nandtool/configs/Mitshubishi_NR242_noecc.toml
nandtool/configs/Scania_AUS4.toml
nandtool/configs/TI_AM335x_nonstrict.toml
nandtool/configs/Toyota_Touch_2_Go.toml
nandtool/configs/Toyota_telematics.toml
nandtool/configs/Toyota_telematics_noecc.toml
nandtool/configs/Volkswagen_OCU3.toml
nandtool/configs/Volvo_TCAM.toml
nandtool/configs/example.toml
nandtool/configs/example_noecc.toml
nandtool/logger.py
nandtool/mount.py
nandtool/nand.py
tests/__init__.py
tests/data/test_image.bin
tests/test_nand.py
nandtool-0.3.1.dist-info/METADATA
nandtool-0.3.1.dist-info/WHEEL
nandtool-0.3.1.dist-info/RECORD
