Metadata-Version: 2.1
Name: nandtool
Version: 0.3.1
Summary: ECC correction for NAND flash
Home-page: https://github.com/NetherlandsForensicInstitute/nandtool
License: Apache-2.0
Keywords: ecc,nand
Author: Francis Hoogendijk
Author-email: f.hoogendijk@nfi.nl
Requires-Python: >=3.8,<4.0
Classifier: License :: OSI Approved :: Apache Software License
Classifier: Programming Language :: Python :: 3
Classifier: Programming Language :: Python :: 3.8
Classifier: Programming Language :: Python :: 3.9
Classifier: Programming Language :: Python :: 3.10
Classifier: Programming Language :: Python :: 3.11
Classifier: Programming Language :: Python :: 3.12
Requires-Dist: bchlib (==1.0.0)
Requires-Dist: crcmod (>=1.7,<2.0)
Requires-Dist: dynaconf (>=3.1.11,<4.0.0)
Requires-Dist: fusepy (>=3.0.1,<4.0.0)
Requires-Dist: numpy (>=1.24.2,<2.0.0)
Requires-Dist: pytest (>=7.2.1,<8.0.0)
Requires-Dist: tqdm (>=4.64.1,<5.0.0)
Project-URL: Repository, https://github.com/NetherlandsForensicInstitute/nandtool
